van/__init__.py
van/ascii_art.txt
van/banik.py
van/image.jpeg
vanrickshaw/__init__.py
vanrickshaw/banik.py
vanrickshaw-0.2.dist-info/METADATA
vanrickshaw-0.2.dist-info/WHEEL
vanrickshaw-0.2.dist-info/entry_points.txt
vanrickshaw-0.2.dist-info/top_level.txt
vanrickshaw-0.2.dist-info/RECORD
