Metadata-Version: 2.4
Name: vanrickshaw
Version: 0.2
Summary: Rickshaw ASCII art animation in terminal
Author: Souparno
Requires-Dist: Pillow
Dynamic: author
Dynamic: requires-dist
Dynamic: summary
